mojito.py
mojito_watcher-1.0.0.dist-info/METADATA
mojito_watcher-1.0.0.dist-info/WHEEL
mojito_watcher-1.0.0.dist-info/entry_points.txt
mojito_watcher-1.0.0.dist-info/top_level.txt
mojito_watcher-1.0.0.dist-info/RECORD
