Metadata-Version: 2.4
Name: mojito-watcher
Version: 1.0.0
Summary: A beautifully simple, zero dependency, fresh file monitoring tool. Monitor file changes in real time with ease using Mojito🍹!
Author-email: cockasian22	 <126391442+cockasian22@users.noreply.github.com>
License: MIT
Classifier: Environment :: Console
Classifier: Programming Language :: Python :: 3
Classifier: Operating System :: OS Independent
Requires-Python: >=3.8
